subsalt/__init__.py
subsalt/client.py
subsalt-0.2.2.dist-info/LICENSE
subsalt-0.2.2.dist-info/METADATA
subsalt-0.2.2.dist-info/WHEEL
subsalt-0.2.2.dist-info/top_level.txt
subsalt-0.2.2.dist-info/RECORD
