Metadata-Version: 2.1
Name: subsalt
Version: 0.2.2
Summary: Convenience wrapper for accessing Subsalt datastore
Home-page: https://github.com/subsalt/subsalt-python
Author: Subsalt team
Author-email: luke@getsubsalt.com
License: UNKNOWN
Project-URL: Bug Tracker, https://github.com/subsalt/subsalt-python/issues
Platform: UNKNOWN
Classifier: Programming Language :: Python :: 3
Classifier: License :: OSI Approved :: MIT License
Classifier: Operating System :: OS Independent
Requires-Python: >=3.6
License-File: LICENSE
Requires-Dist: pandas
Requires-Dist: psycopg2
Requires-Dist: requests
